{"OutputFileHashSum":"535003F18061179E58EBEEC0AE5CC23C92DA3E60D15D93DEE264BF69E42F3624","Converted":true,"OutputModifyDate":"2020-08-28T05:24:39.4463933Z","Metadatas":[],"MetadataTypes":[{"CategoryName":"VuGen.Replay","MetadataTypeName":"HP.LR.Vugen.Iteration","Id":1},{"CategoryName":"VuGen.Replay","MetadataTypeName":"HP.LR.Vugen.NotifyTransaction","Id":2},{"CategoryName":"VuGen.Replay","MetadataTypeName":"Utt.Debugger.Warning","Id":3},{"CategoryName":"VuGen.Replay","MetadataTypeName":"Utt.Debugger.Error","Id":4},{"CategoryName":"VuGen.Replay","MetadataTypeName":"HP.LR.Vugen.NotifyAny","Id":5}]}